nlib3/__init__.py
nlib3/nlib.py
nlib3-1.21.0.dist-info/licenses/LICENSE
nlib3-1.21.0.dist-info/METADATA
nlib3-1.21.0.dist-info/WHEEL
nlib3-1.21.0.dist-info/top_level.txt
nlib3-1.21.0.dist-info/RECORD
