Metadata-Version: 2.4
Name: nlib3
Version: 1.21.0
Summary: You can use a slightly useful function.
Home-page: https://github.com/nicoyou/nlib
Author: nicoyou
Author-email: nicoyou.info@gmail.com
License: MIT
Keywords: nlib3 nlib library utility nicoyou_lib nicoyou
Classifier: Programming Language :: Python
Classifier: Programming Language :: Python :: 3
Classifier: Programming Language :: Python :: 3 :: Only
Classifier: Programming Language :: Python :: 3.11
Classifier: Programming Language :: Python :: 3.12
Classifier: Programming Language :: Python :: 3.13
License-File: LICENSE
Dynamic: author
Dynamic: author-email
Dynamic: classifier
Dynamic: description
Dynamic: description-content-type
Dynamic: home-page
Dynamic: keywords
Dynamic: license
Dynamic: license-file
Dynamic: summary
